{
  "source": {
    "include": [
    ]
  },
  "opts": {
    "access": ["public"],
    "tutorials": "./tutorials",
    "template": "../clean-jsdoc-theme",
    "encoding": "utf8",
    "recurse": false,
    "verbose": true,
    "destination": "../dist/game-tutorials/",
    "mainpagetitle": "Croquet Microverse"
  },
  "plugins": ["plugins/markdown"],
  "markdown": {
    "parser": "gfm",
    "hardwrap": false,
    "idInHeadings": true
  },
  "templates": {
    "cleverLinks": false,
    "monospaceLinks": false,
    "default": {
      "outputSourceFiles": false,
      "includeDate": false,
      "useLongnameInNav": true,
      "staticFiles": {
        "include": [
          "tutorials"
        ],
        "includePattern": "\\.(png|jpg|svg|gif)$"
      }
    }
  }
}
